setup.py
HMF_test_folder/Binomialdistribution.py
HMF_test_folder/Gaussiandistribution.py
HMF_test_folder/Generaldistribution.py
HMF_test_folder/__init__.py
HMF_test_folder.egg-info/PKG-INFO
HMF_test_folder.egg-info/SOURCES.txt
HMF_test_folder.egg-info/dependency_links.txt
HMF_test_folder.egg-info/not-zip-safe
HMF_test_folder.egg-info/top_level.txt